{
  "manifestVersion": "3.2",
  "impls": {
    "52689375fbce0e15632e0c6d594638af666d7f83cb3bab69d00387a0e79fe6a0": {
      "address": "0x91f557ea085525e3eC6Ce4d91528B4760615B12a",
      "txHash": "0x2a708acf9fd178f634cf114be93498dc15034065561ca96bbb73d5ffa32d8fee",
      "layout": {
        "storage": [
          {
            "contract": "Initializable",
            "label": "_initialized",
            "type": "t_bool",
            "src": "@openzeppelin/contracts-upgradeable/proxy/Initializable.sol:24"
          },
          {
            "contract": "Initializable",
            "label": "_initializing",
            "type": "t_bool",
            "src": "@openzeppelin/contracts-upgradeable/proxy/Initializable.sol:29"
          },
          {
            "contract": "LnAdminUpgradeable",
            "label": "admin",
            "type": "t_address",
            "src": "contracts/upgradeable/LnAdminUpgradeable.sol:16"
          },
          {
            "contract": "LnAdminUpgradeable",
            "label": "candidate",
            "type": "t_address",
            "src": "contracts/upgradeable/LnAdminUpgradeable.sol:17"
          },
          {
            "contract": "LnAdminUpgradeable",
            "label": "__gap",
            "type": "t_array(t_uint256)48_storage",
            "src": "contracts/upgradeable/LnAdminUpgradeable.sol:44"
          },
          {
            "contract": "LnDefaultPrices",
            "label": "oracle",
            "type": "t_address",
            "src": "contracts/LnDefaultPrices.sol:13"
          },
          {
            "contract": "LnDefaultPrices",
            "label": "stalePeriod",
            "type": "t_uint256",
            "src": "contracts/LnDefaultPrices.sol:15"
          },
          {
            "contract": "LnDefaultPrices",
            "label": "mPricesLastRound",
            "type": "t_mapping(t_bytes32,t_uint256)",
            "src": "contracts/LnDefaultPrices.sol:17"
          },
          {
            "contract": "LnDefaultPrices",
            "label": "mPricesStorage",
            "type": "t_mapping(t_bytes32,t_mapping(t_uint256,t_struct(PriceData)7110_storage))",
            "src": "contracts/LnDefaultPrices.sol:24"
          },
          {
            "contract": "LnDefaultPrices",
            "label": "__gap",
            "type": "t_array(t_uint256)46_storage",
            "src": "contracts/LnDefaultPrices.sol:182"
          }
        ],
        "types": {
          "t_address": {
            "label": "address"
          },
          "t_uint256": {
            "label": "uint256"
          },
          "t_mapping(t_bytes32,t_uint256)": {
            "label": "mapping(bytes32 => uint256)"
          },
          "t_mapping(t_bytes32,t_mapping(t_uint256,t_struct(PriceData)7110_storage))": {
            "label": "mapping(bytes32 => mapping(uint256 => struct LnDefaultPrices.PriceData))"
          },
          "t_array(t_uint256)46_storage": {
            "label": "uint256[46]"
          },
          "t_array(t_uint256)48_storage": {
            "label": "uint256[48]"
          },
          "t_bool": {
            "label": "bool"
          }
        }
      }
    },
    "feab500ea1b74575aa614286e87b3312ba9f7e56335083fcab3416726161d6cd": {
      "address": "0x7869708D4BEd140875eab03e8b4ECea1e47D7742",
      "txHash": "0x576586b09442177eaf4ef7efb7042e9d36fc47b393626c59a7048f336ec453b8",
      "layout": {
        "storage": [
          {
            "contract": "Initializable",
            "label": "_initialized",
            "type": "t_bool",
            "src": "@openzeppelin/contracts-upgradeable/proxy/Initializable.sol:24"
          },
          {
            "contract": "Initializable",
            "label": "_initializing",
            "type": "t_bool",
            "src": "@openzeppelin/contracts-upgradeable/proxy/Initializable.sol:29"
          },
          {
            "contract": "LnAdminUpgradeable",
            "label": "admin",
            "type": "t_address",
            "src": "contracts/upgradeable/LnAdminUpgradeable.sol:16"
          },
          {
            "contract": "LnAdminUpgradeable",
            "label": "candidate",
            "type": "t_address",
            "src": "contracts/upgradeable/LnAdminUpgradeable.sol:17"
          },
          {
            "contract": "LnAdminUpgradeable",
            "label": "__gap",
            "type": "t_array(t_uint256)48_storage",
            "src": "contracts/upgradeable/LnAdminUpgradeable.sol:44"
          },
          {
            "contract": "LnDebtSystem",
            "label": "accessCtrl",
            "type": "t_contract(LnAccessControl)3137",
            "src": "contracts/LnDebtSystem.sol:21"
          },
          {
            "contract": "LnDebtSystem",
            "label": "assetSys",
            "type": "t_contract(LnAssetSystem)3796",
            "src": "contracts/LnDebtSystem.sol:22"
          },
          {
            "contract": "LnDebtSystem",
            "label": "feeSystem",
            "type": "t_contract(LnFeeSystem)9805",
            "src": "contracts/LnDebtSystem.sol:23"
          },
          {
            "contract": "LnDebtSystem",
            "label": "userDebtState",
            "type": "t_mapping(t_address,t_struct(DebtData)6557_storage)",
            "src": "contracts/LnDebtSystem.sol:29"
          },
          {
            "contract": "LnDebtSystem",
            "label": "lastDebtFactors",
            "type": "t_mapping(t_uint256,t_uint256)",
            "src": "contracts/LnDebtSystem.sol:32"
          },
          {
            "contract": "LnDebtSystem",
            "label": "debtCurrentIndex",
            "type": "t_uint256",
            "src": "contracts/LnDebtSystem.sol:33"
          },
          {
            "contract": "LnDebtSystem",
            "label": "lastCloseAt",
            "type": "t_uint256",
            "src": "contracts/LnDebtSystem.sol:35"
          },
          {
            "contract": "LnDebtSystem",
            "label": "lastDeletTo",
            "type": "t_uint256",
            "src": "contracts/LnDebtSystem.sol:36"
          },
          {
            "contract": "LnDebtSystem",
            "label": "__gap",
            "type": "t_array(t_uint256)42_storage",
            "src": "contracts/LnDebtSystem.sol:172"
          }
        ],
        "types": {
          "t_contract(LnAccessControl)3137": {
            "label": "contract LnAccessControl"
          },
          "t_contract(LnAssetSystem)3796": {
            "label": "contract LnAssetSystem"
          },
          "t_contract(LnFeeSystem)9805": {
            "label": "contract LnFeeSystem"
          },
          "t_mapping(t_address,t_struct(DebtData)6557_storage)": {
            "label": "mapping(address => struct LnDebtSystem.DebtData)"
          },
          "t_mapping(t_uint256,t_uint256)": {
            "label": "mapping(uint256 => uint256)"
          },
          "t_uint256": {
            "label": "uint256"
          },
          "t_array(t_uint256)42_storage": {
            "label": "uint256[42]"
          },
          "t_address": {
            "label": "address"
          },
          "t_array(t_uint256)48_storage": {
            "label": "uint256[48]"
          },
          "t_bool": {
            "label": "bool"
          }
        }
      }
    },
    "bc320597c37d19f964b30a2c4c7f3ef2780584d206375ccd8f50039a83e8584f": {
      "address": "0xe5174405677D70A2Cce4A13065A370026F3daB66",
      "txHash": "0x11bb5ab649af630dd5a5564de30756e0db1c2730973bd4086f1c95d23b4440a2",
      "layout": {
        "storage": [
          {
            "contract": "Initializable",
            "label": "_initialized",
            "type": "t_bool",
            "src": "@openzeppelin/contracts-upgradeable/proxy/Initializable.sol:24"
          },
          {
            "contract": "Initializable",
            "label": "_initializing",
            "type": "t_bool",
            "src": "@openzeppelin/contracts-upgradeable/proxy/Initializable.sol:29"
          },
          {
            "contract": "LnAdminUpgradeable",
            "label": "admin",
            "type": "t_address",
            "src": "contracts/upgradeable/LnAdminUpgradeable.sol:16"
          },
          {
            "contract": "LnAdminUpgradeable",
            "label": "candidate",
            "type": "t_address",
            "src": "contracts/upgradeable/LnAdminUpgradeable.sol:17"
          },
          {
            "contract": "LnAdminUpgradeable",
            "label": "__gap",
            "type": "t_array(t_uint256)48_storage",
            "src": "contracts/upgradeable/LnAdminUpgradeable.sol:44"
          },
          {
            "contract": "ContextUpgradeable",
            "label": "__gap",
            "type": "t_array(t_uint256)50_storage",
            "src": "@openzeppelin/contracts-upgradeable/GSN/ContextUpgradeable.sol:31"
          },
          {
            "contract": "PausableUpgradeable",
            "label": "_paused",
            "type": "t_bool",
            "src": "@openzeppelin/contracts-upgradeable/utils/PausableUpgradeable.sol:28"
          },
          {
            "contract": "PausableUpgradeable",
            "label": "__gap",
            "type": "t_array(t_uint256)49_storage",
            "src": "@openzeppelin/contracts-upgradeable/utils/PausableUpgradeable.sol:96"
          },
          {
            "contract": "LnCollateralSystem",
            "label": "priceGetter",
            "type": "t_contract(LnPrices)11214",
            "src": "contracts/LnCollateralSystem.sol:28"
          },
          {
            "contract": "LnCollateralSystem",
            "label": "debtSystem",
            "type": "t_contract(LnDebtSystem)7081",
            "src": "contracts/LnCollateralSystem.sol:28"
          },
          {
            "contract": "LnCollateralSystem",
            "label": "buildBurnSystem",
            "type": "t_contract(LnBuildBurnSystem)4540",
            "src": "contracts/LnCollateralSystem.sol:30"
          },
          {
            "contract": "LnCollateralSystem",
            "label": "mConfig",
            "type": "t_contract(LnConfig)6522",
            "src": "contracts/LnCollateralSystem.sol:32"
          },
          {
            "contract": "LnCollateralSystem",
            "label": "mRewardLocker",
            "type": "t_contract(LnRewardLocker)12211",
            "src": "contracts/LnCollateralSystem.sol:32"
          },
          {
            "contract": "LnCollateralSystem",
            "label": "uniqueId",
            "type": "t_uint256",
            "src": "contracts/LnCollateralSystem.sol:39"
          },
          {
            "contract": "LnCollateralSystem",
            "label": "tokenInfos",
            "type": "t_mapping(t_bytes32,t_struct(TokenInfo)4975_storage)",
            "src": "contracts/LnCollateralSystem.sol:46"
          },
          {
            "contract": "LnCollateralSystem",
            "label": "tokenSymbol",
            "type": "t_array(t_bytes32)dyn_storage",
            "src": "contracts/LnCollateralSystem.sol:49"
          },
          {
            "contract": "LnCollateralSystem",
            "label": "userCollateralData",
            "type": "t_mapping(t_address,t_mapping(t_bytes32,t_struct(CollateralData)4985_storage))",
            "src": "contracts/LnCollateralSystem.sol:55"
          },
          {
            "contract": "LnCollateralSystem",
            "label": "__gap",
            "type": "t_array(t_uint256)41_storage",
            "src": "contracts/LnCollateralSystem.sol:332"
          }
        ],
        "types": {
          "t_contract(LnPrices)11214": {
            "label": "contract LnPrices"
          },
          "t_contract(LnDebtSystem)7081": {
            "label": "contract LnDebtSystem"
          },
          "t_contract(LnBuildBurnSystem)4540": {
            "label": "contract LnBuildBurnSystem"
          },
          "t_contract(LnConfig)6522": {
            "label": "contract LnConfig"
          },
          "t_contract(LnRewardLocker)12211": {
            "label": "contract LnRewardLocker"
          },
          "t_uint256": {
            "label": "uint256"
          },
          "t_mapping(t_bytes32,t_struct(TokenInfo)4975_storage)": {
            "label": "mapping(bytes32 => struct LnCollateralSystem.TokenInfo)"
          },
          "t_array(t_bytes32)dyn_storage": {
            "label": "bytes32[]"
          },
          "t_mapping(t_address,t_mapping(t_bytes32,t_struct(CollateralData)4985_storage))": {
            "label": "mapping(address => mapping(bytes32 => struct LnCollateralSystem.CollateralData))"
          },
          "t_array(t_uint256)41_storage": {
            "label": "uint256[41]"
          },
          "t_bool": {
            "label": "bool"
          },
          "t_array(t_uint256)49_storage": {
            "label": "uint256[49]"
          },
          "t_array(t_uint256)50_storage": {
            "label": "uint256[50]"
          },
          "t_address": {
            "label": "address"
          },
          "t_array(t_uint256)48_storage": {
            "label": "uint256[48]"
          }
        }
      }
    },
    "f09d65f4e13bfcac29fa5379fbb525262e5f03c69b1c2f34832b92c9a7bfae01": {
      "address": "0x15dE97DA354c26fb896f1B6C8eD08Bde7CE06046",
      "txHash": "0x44e551d3a99e0fe084eabcd5f603589664821a9f684b2640143509d856273c95",
      "layout": {
        "storage": [
          {
            "contract": "Initializable",
            "label": "_initialized",
            "type": "t_bool",
            "src": "@openzeppelin/contracts-upgradeable/proxy/Initializable.sol:24"
          },
          {
            "contract": "Initializable",
            "label": "_initializing",
            "type": "t_bool",
            "src": "@openzeppelin/contracts-upgradeable/proxy/Initializable.sol:29"
          },
          {
            "contract": "LnAdminUpgradeable",
            "label": "admin",
            "type": "t_address",
            "src": "contracts/upgradeable/LnAdminUpgradeable.sol:16"
          },
          {
            "contract": "LnAdminUpgradeable",
            "label": "candidate",
            "type": "t_address",
            "src": "contracts/upgradeable/LnAdminUpgradeable.sol:17"
          },
          {
            "contract": "LnAdminUpgradeable",
            "label": "__gap",
            "type": "t_array(t_uint256)48_storage",
            "src": "contracts/upgradeable/LnAdminUpgradeable.sol:44"
          },
          {
            "contract": "LnFeeSystem",
            "label": "curRewardPeriod",
            "type": "t_struct(RewardPeriod)8859_storage",
            "src": "contracts/LnFeeSystem.sol:37"
          },
          {
            "contract": "LnFeeSystem",
            "label": "preRewardPeriod",
            "type": "t_struct(RewardPeriod)8859_storage",
            "src": "contracts/LnFeeSystem.sol:38"
          },
          {
            "contract": "LnFeeSystem",
            "label": "OnePeriodSecs",
            "type": "t_uint256",
            "src": "contracts/LnFeeSystem.sol:39"
          },
          {
            "contract": "LnFeeSystem",
            "label": "LockTime",
            "type": "t_uint64",
            "src": "contracts/LnFeeSystem.sol:41"
          },
          {
            "contract": "LnFeeSystem",
            "label": "userLastClaimedId",
            "type": "t_mapping(t_address,t_uint256)",
            "src": "contracts/LnFeeSystem.sol:41"
          },
          {
            "contract": "LnFeeSystem",
            "label": "userPeriodDebt",
            "type": "t_mapping(t_address,t_array(t_struct(UserDebtData)8844_storage)2_storage)",
            "src": "contracts/LnFeeSystem.sol:43"
          },
          {
            "contract": "LnFeeSystem",
            "label": "debtSystem",
            "type": "t_contract(LnDebtSystem)7081",
            "src": "contracts/LnFeeSystem.sol:47"
          },
          {
            "contract": "LnFeeSystem",
            "label": "collateralSystem",
            "type": "t_contract(LnCollateralSystem)6390",
            "src": "contracts/LnFeeSystem.sol:48"
          },
          {
            "contract": "LnFeeSystem",
            "label": "rewardLocker",
            "type": "t_contract(LnRewardLocker)12211",
            "src": "contracts/LnFeeSystem.sol:49"
          },
          {
            "contract": "LnFeeSystem",
            "label": "mAssets",
            "type": "t_contract(LnAssetSystem)3796",
            "src": "contracts/LnFeeSystem.sol:51"
          },
          {
            "contract": "LnFeeSystem",
            "label": "exchangeSystemAddress",
            "type": "t_address",
            "src": "contracts/LnFeeSystem.sol:52"
          },
          {
            "contract": "LnFeeSystem",
            "label": "rewardDistributer",
            "type": "t_address",
            "src": "contracts/LnFeeSystem.sol:54"
          },
          {
            "contract": "LnFeeSystem",
            "label": "__gap",
            "type": "t_array(t_uint256)38_storage",
            "src": "contracts/LnFeeSystem.sol:297"
          }
        ],
        "types": {
          "t_struct(RewardPeriod)8859_storage": {
            "label": "struct LnFeeSystem.RewardPeriod"
          },
          "t_uint256": {
            "label": "uint256"
          },
          "t_uint64": {
            "label": "uint64"
          },
          "t_mapping(t_address,t_uint256)": {
            "label": "mapping(address => uint256)"
          },
          "t_mapping(t_address,t_array(t_struct(UserDebtData)8844_storage)2_storage)": {
            "label": "mapping(address => struct LnFeeSystem.UserDebtData[2])"
          },
          "t_contract(LnDebtSystem)7081": {
            "label": "contract LnDebtSystem"
          },
          "t_contract(LnCollateralSystem)6390": {
            "label": "contract LnCollateralSystem"
          },
          "t_contract(LnRewardLocker)12211": {
            "label": "contract LnRewardLocker"
          },
          "t_contract(LnAssetSystem)3796": {
            "label": "contract LnAssetSystem"
          },
          "t_address": {
            "label": "address"
          },
          "t_array(t_uint256)38_storage": {
            "label": "uint256[38]"
          },
          "t_array(t_uint256)48_storage": {
            "label": "uint256[48]"
          },
          "t_bool": {
            "label": "bool"
          }
        }
      }
    },
    "8dd82e065b0231bd8555410758b73a512f064ce218c889b9148068e1914dc729": {
      "address": "0x3F9bc2A7d56d4B4b7c8Aadc69796AeA61FeE0045",
      "txHash": "0x3c63bd163704c158d3348253608feeb993ccd3e6c1464615ea9e12bbef2c06d5",
      "layout": {
        "storage": [
          {
            "contract": "Initializable",
            "label": "_initialized",
            "type": "t_bool",
            "src": "@openzeppelin/contracts-upgradeable/proxy/Initializable.sol:24"
          },
          {
            "contract": "Initializable",
            "label": "_initializing",
            "type": "t_bool",
            "src": "@openzeppelin/contracts-upgradeable/proxy/Initializable.sol:29"
          },
          {
            "contract": "LnAdminUpgradeable",
            "label": "admin",
            "type": "t_address",
            "src": "contracts/upgradeable/LnAdminUpgradeable.sol:16"
          },
          {
            "contract": "LnAdminUpgradeable",
            "label": "candidate",
            "type": "t_address",
            "src": "contracts/upgradeable/LnAdminUpgradeable.sol:17"
          },
          {
            "contract": "LnAdminUpgradeable",
            "label": "__gap",
            "type": "t_array(t_uint256)48_storage",
            "src": "contracts/upgradeable/LnAdminUpgradeable.sol:44"
          },
          {
            "contract": "LnRewardLocker",
            "label": "userRewards",
            "type": "t_mapping(t_address,t_array(t_struct(RewardData)11801_storage)dyn_storage)",
            "src": "contracts/LnRewardLocker.sol:17"
          },
          {
            "contract": "LnRewardLocker",
            "label": "balanceOf",
            "type": "t_mapping(t_address,t_uint256)",
            "src": "contracts/LnRewardLocker.sol:18"
          },
          {
            "contract": "LnRewardLocker",
            "label": "totalNeedToReward",
            "type": "t_uint256",
            "src": "contracts/LnRewardLocker.sol:19"
          },
          {
            "contract": "LnRewardLocker",
            "label": "feeSysAddr",
            "type": "t_address",
            "src": "contracts/LnRewardLocker.sol:23"
          },
          {
            "contract": "LnRewardLocker",
            "label": "linaToken",
            "type": "t_contract(IERC20)2682",
            "src": "contracts/LnRewardLocker.sol:24"
          },
          {
            "contract": "LnRewardLocker",
            "label": "__gap",
            "type": "t_array(t_uint256)45_storage",
            "src": "contracts/LnRewardLocker.sol:120"
          }
        ],
        "types": {
          "t_mapping(t_address,t_array(t_struct(RewardData)11801_storage)dyn_storage)": {
            "label": "mapping(address => struct LnRewardLocker.RewardData[])"
          },
          "t_mapping(t_address,t_uint256)": {
            "label": "mapping(address => uint256)"
          },
          "t_uint256": {
            "label": "uint256"
          },
          "t_address": {
            "label": "address"
          },
          "t_contract(IERC20)2682": {
            "label": "contract IERC20"
          },
          "t_array(t_uint256)45_storage": {
            "label": "uint256[45]"
          },
          "t_array(t_uint256)48_storage": {
            "label": "uint256[48]"
          },
          "t_bool": {
            "label": "bool"
          }
        }
      }
    },
    "6cfbaf77129e855799a490b9bcdde11451b7cbdf27a00e04c910d20624aa3017": {
      "address": "0x79BD88042550e980b18330409575e318963b87FC",
      "txHash": "0xf6ebf0bd40db24b406a9f9bbbe56295d201c937024a20977346345bdbe4eca10",
      "layout": {
        "storage": [
          {
            "contract": "Initializable",
            "label": "_initialized",
            "type": "t_bool",
            "src": "@openzeppelin/contracts-upgradeable/proxy/Initializable.sol:24"
          },
          {
            "contract": "Initializable",
            "label": "_initializing",
            "type": "t_bool",
            "src": "@openzeppelin/contracts-upgradeable/proxy/Initializable.sol:29"
          },
          {
            "contract": "ContextUpgradeable",
            "label": "__gap",
            "type": "t_array(t_uint256)50_storage",
            "src": "@openzeppelin/contracts-upgradeable/GSN/ContextUpgradeable.sol:31"
          },
          {
            "contract": "ERC20Upgradeable",
            "label": "_balances",
            "type": "t_mapping(t_address,t_uint256)",
            "src": "@openzeppelin/contracts-upgradeable/token/ERC20/ERC20Upgradeable.sol:37"
          },
          {
            "contract": "ERC20Upgradeable",
            "label": "_allowances",
            "type": "t_mapping(t_address,t_mapping(t_address,t_uint256))",
            "src": "@openzeppelin/contracts-upgradeable/token/ERC20/ERC20Upgradeable.sol:39"
          },
          {
            "contract": "ERC20Upgradeable",
            "label": "_totalSupply",
            "type": "t_uint256",
            "src": "@openzeppelin/contracts-upgradeable/token/ERC20/ERC20Upgradeable.sol:41"
          },
          {
            "contract": "ERC20Upgradeable",
            "label": "_name",
            "type": "t_string_storage",
            "src": "@openzeppelin/contracts-upgradeable/token/ERC20/ERC20Upgradeable.sol:43"
          },
          {
            "contract": "ERC20Upgradeable",
            "label": "_symbol",
            "type": "t_string_storage",
            "src": "@openzeppelin/contracts-upgradeable/token/ERC20/ERC20Upgradeable.sol:44"
          },
          {
            "contract": "ERC20Upgradeable",
            "label": "_decimals",
            "type": "t_uint8",
            "src": "@openzeppelin/contracts-upgradeable/token/ERC20/ERC20Upgradeable.sol:45"
          },
          {
            "contract": "ERC20Upgradeable",
            "label": "__gap",
            "type": "t_array(t_uint256)44_storage",
            "src": "@openzeppelin/contracts-upgradeable/token/ERC20/ERC20Upgradeable.sol:312"
          },
          {
            "contract": "LnAdminUpgradeable",
            "label": "admin",
            "type": "t_address",
            "src": "contracts/upgradeable/LnAdminUpgradeable.sol:16"
          },
          {
            "contract": "LnAdminUpgradeable",
            "label": "candidate",
            "type": "t_address",
            "src": "contracts/upgradeable/LnAdminUpgradeable.sol:17"
          },
          {
            "contract": "LnAdminUpgradeable",
            "label": "__gap",
            "type": "t_array(t_uint256)48_storage",
            "src": "contracts/upgradeable/LnAdminUpgradeable.sol:44"
          },
          {
            "contract": "LnAssetUpgradeable",
            "label": "mKeyName",
            "type": "t_bytes32",
            "src": "contracts/LnAssetUpgradeable.sol:16"
          },
          {
            "contract": "LnAssetUpgradeable",
            "label": "accessCtrl",
            "type": "t_contract(LnAccessControl)3137",
            "src": "contracts/LnAssetUpgradeable.sol:17"
          },
          {
            "contract": "LnAssetUpgradeable",
            "label": "__gap",
            "type": "t_array(t_uint256)48_storage",
            "src": "contracts/LnAssetUpgradeable.sol:61"
          }
        ],
        "types": {
          "t_bytes32": {
            "label": "bytes32"
          },
          "t_contract(LnAccessControl)3137": {
            "label": "contract LnAccessControl"
          },
          "t_array(t_uint256)48_storage": {
            "label": "uint256[48]"
          },
          "t_address": {
            "label": "address"
          },
          "t_mapping(t_address,t_uint256)": {
            "label": "mapping(address => uint256)"
          },
          "t_mapping(t_address,t_mapping(t_address,t_uint256))": {
            "label": "mapping(address => mapping(address => uint256))"
          },
          "t_uint256": {
            "label": "uint256"
          },
          "t_string_storage": {
            "label": "string"
          },
          "t_uint8": {
            "label": "uint8"
          },
          "t_array(t_uint256)44_storage": {
            "label": "uint256[44]"
          },
          "t_array(t_uint256)50_storage": {
            "label": "uint256[50]"
          },
          "t_bool": {
            "label": "bool"
          }
        }
      }
    },
    "a30c6f7a57105e5247eaabc8a11fce0318b37f041170db7744e45257056f6650": {
      "address": "0x05F52746231a79A7f5c8F27ea7f8e3fdc5a784db",
      "txHash": "0x3c928b0e7d594c2a0ceb5aaae247f29b925abbfd6981174251f5b2e0ddcdbe79",
      "layout": {
        "storage": [
          {
            "contract": "Initializable",
            "label": "_initialized",
            "type": "t_bool",
            "src": "@openzeppelin/contracts-upgradeable/proxy/Initializable.sol:24"
          },
          {
            "contract": "Initializable",
            "label": "_initializing",
            "type": "t_bool",
            "src": "@openzeppelin/contracts-upgradeable/proxy/Initializable.sol:29"
          },
          {
            "contract": "LnAdminUpgradeable",
            "label": "admin",
            "type": "t_address",
            "src": "contracts/upgradeable/LnAdminUpgradeable.sol:16"
          },
          {
            "contract": "LnAdminUpgradeable",
            "label": "candidate",
            "type": "t_address",
            "src": "contracts/upgradeable/LnAdminUpgradeable.sol:17"
          },
          {
            "contract": "LnAdminUpgradeable",
            "label": "__gap",
            "type": "t_array(t_uint256)48_storage",
            "src": "contracts/upgradeable/LnAdminUpgradeable.sol:44"
          },
          {
            "contract": "ContextUpgradeable",
            "label": "__gap",
            "type": "t_array(t_uint256)50_storage",
            "src": "@openzeppelin/contracts-upgradeable/GSN/ContextUpgradeable.sol:31"
          },
          {
            "contract": "PausableUpgradeable",
            "label": "_paused",
            "type": "t_bool",
            "src": "@openzeppelin/contracts-upgradeable/utils/PausableUpgradeable.sol:28"
          },
          {
            "contract": "PausableUpgradeable",
            "label": "__gap",
            "type": "t_array(t_uint256)49_storage",
            "src": "@openzeppelin/contracts-upgradeable/utils/PausableUpgradeable.sol:96"
          },
          {
            "contract": "LnCollateralSystem",
            "label": "priceGetter",
            "type": "t_contract(LnPrices)12694",
            "src": "contracts/LnCollateralSystem.sol:28"
          },
          {
            "contract": "LnCollateralSystem",
            "label": "debtSystem",
            "type": "t_contract(LnDebtSystem)8561",
            "src": "contracts/LnCollateralSystem.sol:28"
          },
          {
            "contract": "LnCollateralSystem",
            "label": "buildBurnSystem",
            "type": "t_contract(LnBuildBurnSystem)5906",
            "src": "contracts/LnCollateralSystem.sol:30"
          },
          {
            "contract": "LnCollateralSystem",
            "label": "mConfig",
            "type": "t_contract(LnConfig)8002",
            "src": "contracts/LnCollateralSystem.sol:32"
          },
          {
            "contract": "LnCollateralSystem",
            "label": "mRewardLocker",
            "type": "t_contract(LnRewardLocker)13821",
            "src": "contracts/LnCollateralSystem.sol:32"
          },
          {
            "contract": "LnCollateralSystem",
            "label": "uniqueId",
            "type": "t_uint256",
            "src": "contracts/LnCollateralSystem.sol:39"
          },
          {
            "contract": "LnCollateralSystem",
            "label": "tokenInfos",
            "type": "t_mapping(t_bytes32,t_struct(TokenInfo)6341_storage)",
            "src": "contracts/LnCollateralSystem.sol:46"
          },
          {
            "contract": "LnCollateralSystem",
            "label": "tokenSymbol",
            "type": "t_array(t_bytes32)dyn_storage",
            "src": "contracts/LnCollateralSystem.sol:49"
          },
          {
            "contract": "LnCollateralSystem",
            "label": "userCollateralData",
            "type": "t_mapping(t_address,t_mapping(t_bytes32,t_struct(CollateralData)6351_storage))",
            "src": "contracts/LnCollateralSystem.sol:55"
          },
          {
            "contract": "LnCollateralSystem",
            "label": "__gap",
            "type": "t_array(t_uint256)41_storage",
            "src": "contracts/LnCollateralSystem.sol:357"
          }
        ],
        "types": {
          "t_contract(LnPrices)12694": {
            "label": "contract LnPrices"
          },
          "t_contract(LnDebtSystem)8561": {
            "label": "contract LnDebtSystem"
          },
          "t_contract(LnBuildBurnSystem)5906": {
            "label": "contract LnBuildBurnSystem"
          },
          "t_contract(LnConfig)8002": {
            "label": "contract LnConfig"
          },
          "t_contract(LnRewardLocker)13821": {
            "label": "contract LnRewardLocker"
          },
          "t_uint256": {
            "label": "uint256"
          },
          "t_mapping(t_bytes32,t_struct(TokenInfo)6341_storage)": {
            "label": "mapping(bytes32 => struct LnCollateralSystem.TokenInfo)"
          },
          "t_array(t_bytes32)dyn_storage": {
            "label": "bytes32[]"
          },
          "t_mapping(t_address,t_mapping(t_bytes32,t_struct(CollateralData)6351_storage))": {
            "label": "mapping(address => mapping(bytes32 => struct LnCollateralSystem.CollateralData))"
          },
          "t_array(t_uint256)41_storage": {
            "label": "uint256[41]"
          },
          "t_bool": {
            "label": "bool"
          },
          "t_array(t_uint256)49_storage": {
            "label": "uint256[49]"
          },
          "t_array(t_uint256)50_storage": {
            "label": "uint256[50]"
          },
          "t_address": {
            "label": "address"
          },
          "t_array(t_uint256)48_storage": {
            "label": "uint256[48]"
          }
        }
      }
    },
    "e493f3e046a81a360e18d252c55242ca04063147e9b4b9c3a01be9724aca8232": {
      "address": "0x99Dc2874A9bE1Cb433C3f7f99E7667c594E7FB5A",
      "txHash": "0x78b7de4d7d170181c943263b81116e0f66038964a9ac7f3609295cdae77ca2a2",
      "layout": {
        "storage": [
          {
            "contract": "Initializable",
            "label": "_initialized",
            "type": "t_bool",
            "src": "@openzeppelin/contracts-upgradeable/proxy/Initializable.sol:24"
          },
          {
            "contract": "Initializable",
            "label": "_initializing",
            "type": "t_bool",
            "src": "@openzeppelin/contracts-upgradeable/proxy/Initializable.sol:29"
          },
          {
            "contract": "LnAdminUpgradeable",
            "label": "admin",
            "type": "t_address",
            "src": "contracts/upgradeable/LnAdminUpgradeable.sol:16"
          },
          {
            "contract": "LnAdminUpgradeable",
            "label": "candidate",
            "type": "t_address",
            "src": "contracts/upgradeable/LnAdminUpgradeable.sol:17"
          },
          {
            "contract": "LnAdminUpgradeable",
            "label": "__gap",
            "type": "t_array(t_uint256)48_storage",
            "src": "contracts/upgradeable/LnAdminUpgradeable.sol:44"
          },
          {
            "contract": "LnRewardLocker",
            "label": "userRewards",
            "type": "t_mapping(t_address,t_array(t_struct(RewardData)13281_storage)dyn_storage)",
            "src": "contracts/LnRewardLocker.sol:17"
          },
          {
            "contract": "LnRewardLocker",
            "label": "balanceOf",
            "type": "t_mapping(t_address,t_uint256)",
            "src": "contracts/LnRewardLocker.sol:18"
          },
          {
            "contract": "LnRewardLocker",
            "label": "totalNeedToReward",
            "type": "t_uint256",
            "src": "contracts/LnRewardLocker.sol:19"
          },
          {
            "contract": "LnRewardLocker",
            "label": "feeSysAddr",
            "type": "t_address",
            "src": "contracts/LnRewardLocker.sol:23"
          },
          {
            "contract": "LnRewardLocker",
            "label": "linaToken",
            "type": "t_contract(IERC20)4048",
            "src": "contracts/LnRewardLocker.sol:24"
          },
          {
            "contract": "LnRewardLocker",
            "label": "__gap",
            "type": "t_array(t_uint256)45_storage",
            "src": "contracts/LnRewardLocker.sol:153"
          }
        ],
        "types": {
          "t_mapping(t_address,t_array(t_struct(RewardData)13281_storage)dyn_storage)": {
            "label": "mapping(address => struct LnRewardLocker.RewardData[])"
          },
          "t_mapping(t_address,t_uint256)": {
            "label": "mapping(address => uint256)"
          },
          "t_uint256": {
            "label": "uint256"
          },
          "t_address": {
            "label": "address"
          },
          "t_contract(IERC20)4048": {
            "label": "contract IERC20"
          },
          "t_array(t_uint256)45_storage": {
            "label": "uint256[45]"
          },
          "t_array(t_uint256)48_storage": {
            "label": "uint256[48]"
          },
          "t_bool": {
            "label": "bool"
          }
        }
      }
    },
    "27238a7b9240cc47add015f368888a519085b260286a05829a6da452f7a4a236": {
      "address": "0x59421d5f1A369ECb905808C6D4650A621d6871Cf",
      "txHash": "0x726114ce9117a1d1ccb442424e921b254ccbe3dfdaf21f7ffe76fd12029af26a",
      "layout": {
        "storage": [
          {
            "contract": "Initializable",
            "label": "_initialized",
            "type": "t_bool",
            "src": "@openzeppelin/contracts-upgradeable/proxy/Initializable.sol:24"
          },
          {
            "contract": "Initializable",
            "label": "_initializing",
            "type": "t_bool",
            "src": "@openzeppelin/contracts-upgradeable/proxy/Initializable.sol:29"
          },
          {
            "contract": "LnAdminUpgradeable",
            "label": "admin",
            "type": "t_address",
            "src": "contracts/upgradeable/LnAdminUpgradeable.sol:16"
          },
          {
            "contract": "LnAdminUpgradeable",
            "label": "candidate",
            "type": "t_address",
            "src": "contracts/upgradeable/LnAdminUpgradeable.sol:17"
          },
          {
            "contract": "LnAdminUpgradeable",
            "label": "__gap",
            "type": "t_array(t_uint256)48_storage",
            "src": "contracts/upgradeable/LnAdminUpgradeable.sol:44"
          },
          {
            "contract": "ContextUpgradeable",
            "label": "__gap",
            "type": "t_array(t_uint256)50_storage",
            "src": "@openzeppelin/contracts-upgradeable/GSN/ContextUpgradeable.sol:31"
          },
          {
            "contract": "PausableUpgradeable",
            "label": "_paused",
            "type": "t_bool",
            "src": "@openzeppelin/contracts-upgradeable/utils/PausableUpgradeable.sol:28"
          },
          {
            "contract": "PausableUpgradeable",
            "label": "__gap",
            "type": "t_array(t_uint256)49_storage",
            "src": "@openzeppelin/contracts-upgradeable/utils/PausableUpgradeable.sol:96"
          },
          {
            "contract": "LnCollateralSystem",
            "label": "priceGetter",
            "type": "t_contract(LnPrices)12658",
            "src": "contracts/LnCollateralSystem.sol:28"
          },
          {
            "contract": "LnCollateralSystem",
            "label": "debtSystem",
            "type": "t_contract(LnDebtSystem)8525",
            "src": "contracts/LnCollateralSystem.sol:28"
          },
          {
            "contract": "LnCollateralSystem",
            "label": "buildBurnSystem",
            "type": "t_contract(LnBuildBurnSystem)5906",
            "src": "contracts/LnCollateralSystem.sol:30"
          },
          {
            "contract": "LnCollateralSystem",
            "label": "mConfig",
            "type": "t_contract(LnConfig)7966",
            "src": "contracts/LnCollateralSystem.sol:32"
          },
          {
            "contract": "LnCollateralSystem",
            "label": "mRewardLocker",
            "type": "t_contract(LnRewardLocker)13785",
            "src": "contracts/LnCollateralSystem.sol:32"
          },
          {
            "contract": "LnCollateralSystem",
            "label": "uniqueId",
            "type": "t_uint256",
            "src": "contracts/LnCollateralSystem.sol:39"
          },
          {
            "contract": "LnCollateralSystem",
            "label": "tokenInfos",
            "type": "t_mapping(t_bytes32,t_struct(TokenInfo)6341_storage)",
            "src": "contracts/LnCollateralSystem.sol:46"
          },
          {
            "contract": "LnCollateralSystem",
            "label": "tokenSymbol",
            "type": "t_array(t_bytes32)dyn_storage",
            "src": "contracts/LnCollateralSystem.sol:49"
          },
          {
            "contract": "LnCollateralSystem",
            "label": "userCollateralData",
            "type": "t_mapping(t_address,t_mapping(t_bytes32,t_struct(CollateralData)6351_storage))",
            "src": "contracts/LnCollateralSystem.sol:55"
          },
          {
            "contract": "LnCollateralSystem",
            "label": "__gap",
            "type": "t_array(t_uint256)41_storage",
            "src": "contracts/LnCollateralSystem.sol:355"
          }
        ],
        "types": {
          "t_contract(LnPrices)12658": {
            "label": "contract LnPrices"
          },
          "t_contract(LnDebtSystem)8525": {
            "label": "contract LnDebtSystem"
          },
          "t_contract(LnBuildBurnSystem)5906": {
            "label": "contract LnBuildBurnSystem"
          },
          "t_contract(LnConfig)7966": {
            "label": "contract LnConfig"
          },
          "t_contract(LnRewardLocker)13785": {
            "label": "contract LnRewardLocker"
          },
          "t_uint256": {
            "label": "uint256"
          },
          "t_mapping(t_bytes32,t_struct(TokenInfo)6341_storage)": {
            "label": "mapping(bytes32 => struct LnCollateralSystem.TokenInfo)"
          },
          "t_array(t_bytes32)dyn_storage": {
            "label": "bytes32[]"
          },
          "t_mapping(t_address,t_mapping(t_bytes32,t_struct(CollateralData)6351_storage))": {
            "label": "mapping(address => mapping(bytes32 => struct LnCollateralSystem.CollateralData))"
          },
          "t_array(t_uint256)41_storage": {
            "label": "uint256[41]"
          },
          "t_bool": {
            "label": "bool"
          },
          "t_array(t_uint256)49_storage": {
            "label": "uint256[49]"
          },
          "t_array(t_uint256)50_storage": {
            "label": "uint256[50]"
          },
          "t_address": {
            "label": "address"
          },
          "t_array(t_uint256)48_storage": {
            "label": "uint256[48]"
          }
        }
      }
    },
    "e1c0ed203e50f2478bd300470a369846ff4233bf52f6d08526594b508de2ae82": {
      "address": "0x2E6f89d3000Ec0a7611E57A6CfB7b825Ab9633A6",
      "txHash": "0xdc7cf0b0c9181d1cd81743aae7c71962d1fe7de312f91c06ab173e42d22c10c0",
      "layout": {
        "storage": [
          {
            "contract": "Initializable",
            "label": "_initialized",
            "type": "t_bool",
            "src": "@openzeppelin/contracts-upgradeable/proxy/Initializable.sol:24"
          },
          {
            "contract": "Initializable",
            "label": "_initializing",
            "type": "t_bool",
            "src": "@openzeppelin/contracts-upgradeable/proxy/Initializable.sol:29"
          },
          {
            "contract": "LnAdminUpgradeable",
            "label": "admin",
            "type": "t_address",
            "src": "contracts/upgradeable/LnAdminUpgradeable.sol:16"
          },
          {
            "contract": "LnAdminUpgradeable",
            "label": "candidate",
            "type": "t_address",
            "src": "contracts/upgradeable/LnAdminUpgradeable.sol:17"
          },
          {
            "contract": "LnAdminUpgradeable",
            "label": "__gap",
            "type": "t_array(t_uint256)48_storage",
            "src": "contracts/upgradeable/LnAdminUpgradeable.sol:44"
          },
          {
            "contract": "LnRewardSystem",
            "label": "firstPeriodStartTime",
            "type": "t_uint256",
            "src": "contracts/LnRewardSystem.sol:27"
          },
          {
            "contract": "LnRewardSystem",
            "label": "rewardSigner",
            "type": "t_address",
            "src": "contracts/LnRewardSystem.sol:28"
          },
          {
            "contract": "LnRewardSystem",
            "label": "userLastClaimPeriodIds",
            "type": "t_mapping(t_address,t_uint256)",
            "src": "contracts/LnRewardSystem.sol:29"
          },
          {
            "contract": "LnRewardSystem",
            "label": "lusd",
            "type": "t_contract(IERC20Upgradeable)919",
            "src": "contracts/LnRewardSystem.sol:31"
          },
          {
            "contract": "LnRewardSystem",
            "label": "collateralSystem",
            "type": "t_contract(ILnCollateralSystem)4038",
            "src": "contracts/LnRewardSystem.sol:32"
          },
          {
            "contract": "LnRewardSystem",
            "label": "rewardLocker",
            "type": "t_contract(ILnRewardLocker)4050",
            "src": "contracts/LnRewardSystem.sol:33"
          },
          {
            "contract": "LnRewardSystem",
            "label": "DOMAIN_SEPARATOR",
            "type": "t_bytes32",
            "src": "contracts/LnRewardSystem.sol:35"
          },
          {
            "contract": "LnRewardSystem",
            "label": "__gap",
            "type": "t_array(t_uint256)43_storage",
            "src": "contracts/LnRewardSystem.sol:192"
          }
        ],
        "types": {
          "t_uint256": {
            "label": "uint256"
          },
          "t_address": {
            "label": "address"
          },
          "t_mapping(t_address,t_uint256)": {
            "label": "mapping(address => uint256)"
          },
          "t_contract(IERC20Upgradeable)919": {
            "label": "contract IERC20Upgradeable"
          },
          "t_contract(ILnCollateralSystem)4038": {
            "label": "contract ILnCollateralSystem"
          },
          "t_contract(ILnRewardLocker)4050": {
            "label": "contract ILnRewardLocker"
          },
          "t_bytes32": {
            "label": "bytes32"
          },
          "t_array(t_uint256)43_storage": {
            "label": "uint256[43]"
          },
          "t_array(t_uint256)48_storage": {
            "label": "uint256[48]"
          },
          "t_bool": {
            "label": "bool"
          }
        }
      }
    },
    "c98346cc8f20b73b950efc6f0e4c86486deeea6b927133eb145e5641e0d2ced6": {
      "address": "0x78574D5aC6469aEd224cB5c1405F5c0F2926e164",
      "txHash": "0x8879429f66894b881d9dd25037e8262d0e5dbaab6f8b788515ef41895da14ce7",
      "layout": {
        "storage": [
          {
            "contract": "Initializable",
            "label": "_initialized",
            "type": "t_bool",
            "src": "@openzeppelin/contracts-upgradeable/proxy/Initializable.sol:24"
          },
          {
            "contract": "Initializable",
            "label": "_initializing",
            "type": "t_bool",
            "src": "@openzeppelin/contracts-upgradeable/proxy/Initializable.sol:29"
          },
          {
            "contract": "LnAdminUpgradeable",
            "label": "admin",
            "type": "t_address",
            "src": "contracts/upgradeable/LnAdminUpgradeable.sol:16"
          },
          {
            "contract": "LnAdminUpgradeable",
            "label": "candidate",
            "type": "t_address",
            "src": "contracts/upgradeable/LnAdminUpgradeable.sol:17"
          },
          {
            "contract": "LnAdminUpgradeable",
            "label": "__gap",
            "type": "t_array(t_uint256)48_storage",
            "src": "contracts/upgradeable/LnAdminUpgradeable.sol:44"
          },
          {
            "contract": "LnErc20Bridge",
            "label": "currentChainId",
            "type": "t_uint256",
            "src": "contracts/LnErc20Bridge.sol:75"
          },
          {
            "contract": "LnErc20Bridge",
            "label": "relayer",
            "type": "t_address",
            "src": "contracts/LnErc20Bridge.sol:76"
          },
          {
            "contract": "LnErc20Bridge",
            "label": "depositCount",
            "type": "t_uint256",
            "src": "contracts/LnErc20Bridge.sol:77"
          },
          {
            "contract": "LnErc20Bridge",
            "label": "tokenInfos",
            "type": "t_mapping(t_bytes32,t_struct(TokenInfo)3196_storage)",
            "src": "contracts/LnErc20Bridge.sol:78"
          },
          {
            "contract": "LnErc20Bridge",
            "label": "tokenSupportedOnChain",
            "type": "t_mapping(t_bytes32,t_mapping(t_uint256,t_bool))",
            "src": "contracts/LnErc20Bridge.sol:79"
          },
          {
            "contract": "LnErc20Bridge",
            "label": "withdrawnDeposits",
            "type": "t_mapping(t_uint256,t_mapping(t_uint256,t_bool))",
            "src": "contracts/LnErc20Bridge.sol:80"
          },
          {
            "contract": "LnErc20Bridge",
            "label": "DOMAIN_SEPARATOR",
            "type": "t_bytes32",
            "src": "contracts/LnErc20Bridge.sol:82"
          }
        ],
        "types": {
          "t_uint256": {
            "label": "uint256"
          },
          "t_address": {
            "label": "address"
          },
          "t_mapping(t_bytes32,t_struct(TokenInfo)3196_storage)": {
            "label": "mapping(bytes32 => struct LnErc20Bridge.TokenInfo)"
          },
          "t_mapping(t_bytes32,t_mapping(t_uint256,t_bool))": {
            "label": "mapping(bytes32 => mapping(uint256 => bool))"
          },
          "t_mapping(t_uint256,t_mapping(t_uint256,t_bool))": {
            "label": "mapping(uint256 => mapping(uint256 => bool))"
          },
          "t_bytes32": {
            "label": "bytes32"
          },
          "t_array(t_uint256)48_storage": {
            "label": "uint256[48]"
          },
          "t_bool": {
            "label": "bool"
          }
        }
      }
    },
    "09cc629a06c2689498f2026125b10e0b840e3f2cfc083e9411a0ebb00c7a9841": {
      "address": "0xC6182b7f3d23140Ca0e4005E97b2AbfaBA3Ed041",
      "txHash": "0x8a29f9ab786f228f1a5afd5396a01dcc9bba1ce2cdaf85de6dec5d5e09a9d2b6",
      "layout": {
        "storage": [
          {
            "contract": "Initializable",
            "label": "_initialized",
            "type": "t_bool",
            "src": "@openzeppelin/contracts-upgradeable/proxy/Initializable.sol:24"
          },
          {
            "contract": "Initializable",
            "label": "_initializing",
            "type": "t_bool",
            "src": "@openzeppelin/contracts-upgradeable/proxy/Initializable.sol:29"
          },
          {
            "contract": "LnAdminUpgradeable",
            "label": "admin",
            "type": "t_address",
            "src": "contracts/upgradeable/LnAdminUpgradeable.sol:16"
          },
          {
            "contract": "LnAdminUpgradeable",
            "label": "candidate",
            "type": "t_address",
            "src": "contracts/upgradeable/LnAdminUpgradeable.sol:17"
          },
          {
            "contract": "LnAdminUpgradeable",
            "label": "__gap",
            "type": "t_array(t_uint256)48_storage",
            "src": "contracts/upgradeable/LnAdminUpgradeable.sol:44"
          },
          {
            "contract": "LnErc20Bridge",
            "label": "currentChainId",
            "type": "t_uint256",
            "src": "contracts/LnErc20Bridge.sol:75"
          },
          {
            "contract": "LnErc20Bridge",
            "label": "relayer",
            "type": "t_address",
            "src": "contracts/LnErc20Bridge.sol:76"
          },
          {
            "contract": "LnErc20Bridge",
            "label": "depositCount",
            "type": "t_uint256",
            "src": "contracts/LnErc20Bridge.sol:77"
          },
          {
            "contract": "LnErc20Bridge",
            "label": "tokenInfos",
            "type": "t_mapping(t_bytes32,t_struct(TokenInfo)3196_storage)",
            "src": "contracts/LnErc20Bridge.sol:78"
          },
          {
            "contract": "LnErc20Bridge",
            "label": "tokenSupportedOnChain",
            "type": "t_mapping(t_bytes32,t_mapping(t_uint256,t_bool))",
            "src": "contracts/LnErc20Bridge.sol:79"
          },
          {
            "contract": "LnErc20Bridge",
            "label": "withdrawnDeposits",
            "type": "t_mapping(t_uint256,t_mapping(t_uint256,t_bool))",
            "src": "contracts/LnErc20Bridge.sol:80"
          },
          {
            "contract": "LnErc20Bridge",
            "label": "DOMAIN_SEPARATOR",
            "type": "t_bytes32",
            "src": "contracts/LnErc20Bridge.sol:82"
          }
        ],
        "types": {
          "t_uint256": {
            "label": "uint256"
          },
          "t_address": {
            "label": "address"
          },
          "t_mapping(t_bytes32,t_struct(TokenInfo)3196_storage)": {
            "label": "mapping(bytes32 => struct LnErc20Bridge.TokenInfo)"
          },
          "t_mapping(t_bytes32,t_mapping(t_uint256,t_bool))": {
            "label": "mapping(bytes32 => mapping(uint256 => bool))"
          },
          "t_mapping(t_uint256,t_mapping(t_uint256,t_bool))": {
            "label": "mapping(uint256 => mapping(uint256 => bool))"
          },
          "t_bytes32": {
            "label": "bytes32"
          },
          "t_array(t_uint256)48_storage": {
            "label": "uint256[48]"
          },
          "t_bool": {
            "label": "bool"
          }
        }
      }
    },
    "624edf3f8afeb57c7e5b34c28c2792e725d09969c29fab23620862178d376eed": {
      "address": "0x0A7Db8e8CEC29625B0E2D1F38fc03a1927e753a6",
      "txHash": "0xa0238cc0baaf0ce241650430010125a7666f1bf567ec1295558880e52cfd8cc5",
      "layout": {
        "storage": [
          {
            "contract": "Initializable",
            "label": "_initialized",
            "type": "t_bool",
            "src": "@openzeppelin/contracts-upgradeable/proxy/Initializable.sol:24"
          },
          {
            "contract": "Initializable",
            "label": "_initializing",
            "type": "t_bool",
            "src": "@openzeppelin/contracts-upgradeable/proxy/Initializable.sol:29"
          },
          {
            "contract": "ContextUpgradeable",
            "label": "__gap",
            "type": "t_array(t_uint256)50_storage",
            "src": "@openzeppelin/contracts-upgradeable/GSN/ContextUpgradeable.sol:31"
          },
          {
            "contract": "ERC20Upgradeable",
            "label": "_balances",
            "type": "t_mapping(t_address,t_uint256)",
            "src": "@openzeppelin/contracts-upgradeable/token/ERC20/ERC20Upgradeable.sol:37"
          },
          {
            "contract": "ERC20Upgradeable",
            "label": "_allowances",
            "type": "t_mapping(t_address,t_mapping(t_address,t_uint256))",
            "src": "@openzeppelin/contracts-upgradeable/token/ERC20/ERC20Upgradeable.sol:39"
          },
          {
            "contract": "ERC20Upgradeable",
            "label": "_totalSupply",
            "type": "t_uint256",
            "src": "@openzeppelin/contracts-upgradeable/token/ERC20/ERC20Upgradeable.sol:41"
          },
          {
            "contract": "ERC20Upgradeable",
            "label": "_name",
            "type": "t_string_storage",
            "src": "@openzeppelin/contracts-upgradeable/token/ERC20/ERC20Upgradeable.sol:43"
          },
          {
            "contract": "ERC20Upgradeable",
            "label": "_symbol",
            "type": "t_string_storage",
            "src": "@openzeppelin/contracts-upgradeable/token/ERC20/ERC20Upgradeable.sol:44"
          },
          {
            "contract": "ERC20Upgradeable",
            "label": "_decimals",
            "type": "t_uint8",
            "src": "@openzeppelin/contracts-upgradeable/token/ERC20/ERC20Upgradeable.sol:45"
          },
          {
            "contract": "ERC20Upgradeable",
            "label": "__gap",
            "type": "t_array(t_uint256)44_storage",
            "src": "@openzeppelin/contracts-upgradeable/token/ERC20/ERC20Upgradeable.sol:312"
          },
          {
            "contract": "LnAdminUpgradeable",
            "label": "admin",
            "type": "t_address",
            "src": "contracts/upgradeable/LnAdminUpgradeable.sol:16"
          },
          {
            "contract": "LnAdminUpgradeable",
            "label": "candidate",
            "type": "t_address",
            "src": "contracts/upgradeable/LnAdminUpgradeable.sol:17"
          },
          {
            "contract": "LnAdminUpgradeable",
            "label": "__gap",
            "type": "t_array(t_uint256)48_storage",
            "src": "contracts/upgradeable/LnAdminUpgradeable.sol:44"
          },
          {
            "contract": "LnAssetUpgradeable",
            "label": "mKeyName",
            "type": "t_bytes32",
            "src": "contracts/LnAssetUpgradeable.sol:15"
          },
          {
            "contract": "LnAssetUpgradeable",
            "label": "accessCtrl",
            "type": "t_contract(ILnAccessControl)10070",
            "src": "contracts/LnAssetUpgradeable.sol:16"
          },
          {
            "contract": "LnAssetUpgradeable",
            "label": "__gap",
            "type": "t_array(t_uint256)48_storage",
            "src": "contracts/LnAssetUpgradeable.sol:78"
          }
        ],
        "types": {
          "t_bytes32": {
            "label": "bytes32"
          },
          "t_contract(ILnAccessControl)10070": {
            "label": "contract ILnAccessControl"
          },
          "t_array(t_uint256)48_storage": {
            "label": "uint256[48]"
          },
          "t_uint256": {
            "label": "uint256"
          },
          "t_address": {
            "label": "address"
          },
          "t_mapping(t_address,t_uint256)": {
            "label": "mapping(address => uint256)"
          },
          "t_mapping(t_address,t_mapping(t_address,t_uint256))": {
            "label": "mapping(address => mapping(address => uint256))"
          },
          "t_string_storage": {
            "label": "string"
          },
          "t_uint8": {
            "label": "uint8"
          },
          "t_array(t_uint256)44_storage": {
            "label": "uint256[44]"
          },
          "t_array(t_uint256)50_storage": {
            "label": "uint256[50]"
          },
          "t_bool": {
            "label": "bool"
          }
        }
      }
    }
  },
  "proxies": [
    {
      "address": "0xBB309BE7fcc989b6eba4769c056daF64eA986832",
      "kind": "transparent",
      "txHash": "0x6f5dc04c187ad434ab2120c94c3add6a71c6ed696b847acc71e8b5e657747dd1"
    },
    {
      "address": "0xe188a69fa25133D5e027EFC5495E3cdb772F01ed",
      "kind": "transparent",
      "txHash": "0x8b86d448f3b60fdab9c795671397fc9c43eb4343c3a5f09cb44756ac6f275ccb"
    },
    {
      "address": "0x1E675438643860A13873cFfB8D1529082515781f",
      "kind": "transparent",
      "txHash": "0x790666001c522dea76b9cfc5e93584aebee2eb9bdfea5838ba3dbbdf497e4607"
    },
    {
      "address": "0xc02e084fEF90032dfaa21ABC0404279a17E82772",
      "kind": "transparent",
      "txHash": "0xf2ac1ce7fff761dab8f8a6bde1fee39435d9e4d633bc4b04b819ed530629323a"
    }
  ],
  "admin": {
    "address": "0x875cD61f6062d160247d7c9159F39D8A7E78e3B5",
    "txHash": "0x48fcafcebc40f5b53b9d85332cdecac13d206ee2a2b5cbdb1c6e30cd1067076e"
  }
}
